<?xml version="1.0" encoding="utf-8"?>
<!DOCTYPE hibernate-mapping PUBLIC "-//Hibernate/Hibernate Mapping DTD 3.0//EN"
"http://hibernate.sourceforge.net/hibernate-mapping-3.0.dtd">
<!-- 
    Mapping file autogenerated by MyEclipse Persistence Tools
-->
<hibernate-mapping>
    <class name="com.nbw.jbxx.domain.XYPJB" table="SMZ_XYPJB" >
        <id name="id" type="java.lang.String">
            <column name="ID" />
            <generator class="native" />
        </id>
        <property name="asscodes" type="java.lang.String">
            <column name="ASSCODES" />
        </property>
        
        <property name="asscomname" type="java.lang.String">
        <column name="ASSCOMNAME"></column>
        </property>
        <property name="asslevel" type="java.lang.String">
        
        <column name="ASSLEVEL"></column>
        </property>
        <property name="asstime"  type="java.util.Date">
        <column name="ASSTIME"></column>
        </property>
        <property name="assdivision" type="java.lang.String">
        <column name="ASSDIVISION"></column>
        </property>
        <property name="assclass" type="java.lang.String">
        <column name="ASSCLASS"></column>
        </property>
        <property name="assid" type="java.lang.String">
        <column name="ASSID"></column>
        </property>
    </class>
</hibernate-mapping>
